asana_cli/__init__.py
asana_cli/__main__.py
asana_cli/main.py
asana_cli/client/__init__.py
asana_cli/client/base.py
asana_cli/client/exceptions.py
asana_cli/commands/__init__.py
asana_cli/commands/config.py
asana_cli/commands/projects.py
asana_cli/commands/sections.py
asana_cli/commands/tasks.py
asana_cli/commands/users.py
asana_cli/commands/workspaces.py
asana_cli/config/__init__.py
asana_cli/config/settings.py
asana_cli/config/storage.py
asana_cli/models/__init__.py
asana_cli/models/base.py
asana_cli/models/project.py
asana_cli/models/responses.py
asana_cli/models/section.py
asana_cli/models/task.py
asana_cli/models/user.py
asana_cli/utils/__init__.py
asana_cli/utils/console.py
asana_cli/utils/formatting.py
py_asana_cli-0.1.0.dist-info/METADATA
py_asana_cli-0.1.0.dist-info/WHEEL
py_asana_cli-0.1.0.dist-info/entry_points.txt
py_asana_cli-0.1.0.dist-info/licenses/LICENSE
py_asana_cli-0.1.0.dist-info/RECORD
