Metadata-Version: 2.4
Name: py-asana-cli
Version: 0.1.0
Summary: A modern CLI for interacting with Asana
Project-URL: Homepage, https://github.com/koenvanderveen/asana-cli
Project-URL: Repository, https://github.com/koenvanderveen/asana-cli
Author-email: Koen van der Veen <koenlennartvanderveen@gmail.com>
License: MIT
License-File: LICENSE
Keywords: asana,cli,productivity,task-management
Classifier: Development Status :: 4 - Beta
Classifier: Environment :: Console
Classifier: Intended Audience :: Developers
Classifier: License :: OSI Approved :: MIT License
Classifier: Programming Language :: Python :: 3.12
Classifier: Programming Language :: Python :: 3.13
Classifier: Topic :: Office/Business :: Scheduling
Requires-Python: >=3.12
Requires-Dist: httpx>=0.27.0
Requires-Dist: pydantic-settings>=2.0.0
Requires-Dist: pydantic>=2.0.0
Requires-Dist: rich>=13.0.0
Requires-Dist: typer>=0.12.0
